cognica/__init__.py
cognica/ml/__init__.py
cognica/ml/nlp/__init__.py
cognica/ml/nlp/sentence_transformer_clip_encoder.py
cognica/ml/nlp/sentence_transformer_cross_encoder.py
cognica/ml/nlp/sentence_transformer_encoder.py
cognica/ml/nlp/sentence_transformer_qa_encoder.py
cognica/permission/__init__.py
cognica/permission/user.py
cognica/server/__init__.py
cognica/server/bootstrap.py
cognica/server/bin/cognica
cognica/server/conf/default.json
cognica/server/etc/mecabrc
cognica/server/lib/libblas.so.3
cognica/server/lib/libboost_atomic.so.1.78.0
cognica/server/lib/libboost_chrono.so.1.78.0
cognica/server/lib/libboost_date_time.so.1.78.0
cognica/server/lib/libboost_filesystem.so.1.78.0
cognica/server/lib/libboost_iostreams.so.1.78.0
cognica/server/lib/libboost_locale.so.1.78.0
cognica/server/lib/libboost_regex.so.1.78.0
cognica/server/lib/libboost_system.so.1.78.0
cognica/server/lib/libboost_thread.so.1.78.0
cognica/server/lib/libbz2.so.1
cognica/server/lib/libcares.so.2
cognica/server/lib/libcom_err.so.2
cognica/server/lib/libcrypt.so.1
cognica/server/lib/libcrypto.so.1.1
cognica/server/lib/libdw.so.1
cognica/server/lib/libelf.so.1
cognica/server/lib/libffi.so.6
cognica/server/lib/libgfortran.so.5
cognica/server/lib/libgomp.so.1
cognica/server/lib/libgssapi_krb5.so.2
cognica/server/lib/libicudata.so.60
cognica/server/lib/libicui18n.so.60
cognica/server/lib/libicuuc.so.60
cognica/server/lib/libjemalloc.so.2
cognica/server/lib/libk5crypto.so.3
cognica/server/lib/libkeyutils.so.1
cognica/server/lib/libkrb5.so.3
cognica/server/lib/libkrb5support.so.0
cognica/server/lib/liblapack.so.3
cognica/server/lib/libluajit-5.1.so.2
cognica/server/lib/liblz4.so.1
cognica/server/lib/liblzma.so.5
cognica/server/lib/libmecab.so.2
cognica/server/lib/libpcre2-8.so.0
cognica/server/lib/libpython3.11.so.1.0
cognica/server/lib/librdkafka++.so.1
cognica/server/lib/librdkafka.so.1
cognica/server/lib/libresolv.so.2
cognica/server/lib/libsasl2.so.3
cognica/server/lib/libselinux.so.1
cognica/server/lib/python3.11/site-packages/pip-23.2.1.dist-info/AUTHORS.txt
cognica/server/lib/python3.11/site-packages/pip-23.2.1.dist-info/INSTALLER
cognica/server/lib/python3.11/site-packages/pip-23.2.1.dist-info/LICENSE.txt
cognica/server/lib/python3.11/site-packages/pip-23.2.1.dist-info/METADATA
cognica/server/lib/python3.11/site-packages/pip-23.2.1.dist-info/RECORD
cognica/server/lib/python3.11/site-packages/pip-23.2.1.dist-info/REQUESTED
cognica/server/lib/python3.11/site-packages/pip-23.2.1.dist-info/WHEEL
cognica/server/lib/python3.11/site-packages/pip-23.2.1.dist-info/entry_points.txt
cognica/server/lib/python3.11/site-packages/pip-23.2.1.dist-info/top_level.txt
cognica/server/lib/python3.11/site-packages/setuptools-65.5.0.dist-info/INSTALLER
cognica/server/lib/python3.11/site-packages/setuptools-65.5.0.dist-info/LICENSE
cognica/server/lib/python3.11/site-packages/setuptools-65.5.0.dist-info/METADATA
cognica/server/lib/python3.11/site-packages/setuptools-65.5.0.dist-info/RECORD
cognica/server/lib/python3.11/site-packages/setuptools-65.5.0.dist-info/REQUESTED
cognica/server/lib/python3.11/site-packages/setuptools-65.5.0.dist-info/WHEEL
cognica/server/lib/python3.11/site-packages/setuptools-65.5.0.dist-info/entry_points.txt
cognica/server/lib/python3.11/site-packages/setuptools-65.5.0.dist-info/top_level.txt
cognica_server-0.1.3.dev5.dist-info/METADATA
cognica_server-0.1.3.dev5.dist-info/WHEEL
cognica_server-0.1.3.dev5.dist-info/entry_points.txt
cognica_server-0.1.3.dev5.dist-info/top_level.txt
cognica_server-0.1.3.dev5.dist-info/RECORD
