Metadata-Version: 2.1
Name: cognica-server
Version: 0.1.3.dev5
Summary: Cognica database
Author: Cognica, Inc.
Author-email: jaepil@cognica.io
Project-URL: Homepage, https://www.cognica.io
Project-URL: Documentation, https://docs.cognica.io
Keywords: Cognica,key-value,document store,full-text search,vector search,search engine,database,deep learning,NLP,natural language processing,transformer,vector embedding
Classifier: Development Status :: 5 - Production/Stable
Classifier: Environment :: Console
Classifier: Intended Audience :: Developers
Classifier: License :: OSI Approved :: Apache Software License
Classifier: Operating System :: OS Independent
Classifier: Programming Language :: Python
Classifier: Programming Language :: Python :: 3
Classifier: Programming Language :: Python :: 3 :: Only
Classifier: Programming Language :: Python :: 3.9
Classifier: Programming Language :: Python :: 3.10
Classifier: Programming Language :: Python :: 3.11
Classifier: Programming Language :: Python :: Implementation :: CPython
Requires-Python: >=3.9
Requires-Dist: torch >=2.1.0
Requires-Dist: torchvision >=0.16.0
Requires-Dist: ftfy
Requires-Dist: transformers
Requires-Dist: sentence-transformers
